pydevDAG
